mud/__init__.py
mud/base.py
mud/cli.py
mud/funs.py
mud/norm.py
mud/plot.py
mud/preprocessing.py
mud/util.py
mud/examples/__init__.py
mud/examples/adcirc.py
mud/examples/comparison.py
mud/examples/examples.py
mud/examples/exp_decay.py
mud/examples/fenics.py
mud/examples/linear.py
mud/examples/poisson.py
mud/examples/simple.py
mud-0.1.2.dist-info/AUTHORS.rst
mud-0.1.2.dist-info/LICENSE.txt
mud-0.1.2.dist-info/METADATA
mud-0.1.2.dist-info/WHEEL
mud-0.1.2.dist-info/entry_points.txt
mud-0.1.2.dist-info/top_level.txt
mud-0.1.2.dist-info/RECORD
