Metadata-Version: 2.1
Name: mud
Version: 0.1.2
Summary: Maximal Updated Density equations for Data-Consistent Inversion
Home-page: https://github.com/mathematicalmichael/mud.git
Author: Mathematical Michael
Author-email: consistentbayes@gmail.com
License: mit
Project-URL: Documentation, https://mud.dataconsistent.com/
Platform: any
Classifier: Development Status :: 4 - Beta
Classifier: Programming Language :: Python
Requires-Python: >=3.7
License-File: LICENSE.txt
License-File: AUTHORS.rst
Requires-Dist: numpy <1.27,>=1.20
Requires-Dist: scipy <2.0,>=1.2
Requires-Dist: matplotlib <4.0,>=1.0
Requires-Dist: scikit-learn <2.0,>=1.0
Requires-Dist: importlib-metadata ; python_version < "3.10"
Provides-Extra: dev
Requires-Dist: black[jupyter] ; extra == 'dev'
Requires-Dist: coverage ; extra == 'dev'
Requires-Dist: coveralls ; extra == 'dev'
Requires-Dist: flake8 ; extra == 'dev'
Requires-Dist: isort ; extra == 'dev'
Requires-Dist: mypy ; extra == 'dev'
Requires-Dist: pre-commit ; extra == 'dev'
Requires-Dist: pytest ; extra == 'dev'
Requires-Dist: pytest-cov ; extra == 'dev'
Provides-Extra: examples
Requires-Dist: click ; extra == 'examples'
Requires-Dist: tqdm ; extra == 'examples'
Requires-Dist: prettytable ; extra == 'examples'
Requires-Dist: pandas <3.0,>=1.2 ; extra == 'examples'
Requires-Dist: wget ; extra == 'examples'
Provides-Extra: pub
Requires-Dist: setuptools ; extra == 'pub'
Requires-Dist: setuptools-scm ; extra == 'pub'
Requires-Dist: wheel ; extra == 'pub'
Requires-Dist: twine ; extra == 'pub'
